pyinstall.py
regen-docs
setup.py
docs/conf.py
docs/index.txt
docs/news.txt
docs/requirement-format.txt
pyinstall.egg-info/PKG-INFO
pyinstall.egg-info/SOURCES.txt
pyinstall.egg-info/dependency_links.txt
pyinstall.egg-info/top_level.txt
tests/test_all_pyinstall.py
tests/test_basic.txt
tests/test_freeze.txt
tests/test_proxy.txt
tests/test_pyinstall.py
tests/test_requirements.txt