Metadata-Version: 1.0
Name: pyinstall
Version: 0.1.4
Summary: Installer for Python packages
Home-page: http://pyinstall.openplans.org
Author: The Open Planning Project
Author-email: python-virtualenv@groups.google.com
License: MIT
Keywords: easy_install distutils setuptools egg virtualenv
Platform: UNKNOWN
Classifier: Development Status :: 4 - Beta
Classifier: Intended Audience :: Developers
Classifier: License :: OSI Approved :: MIT License
Classifier: Topic :: Software Development :: Build Tools
